cardboard/__init__.py
cardboard/blueprints.py
cardboard/cardboard.py
cardboard/cards.py
cardboard/runnable.py
cardboard/server.py
cardboard/sockets.py
cardboard/wsgi.py
cardboard_server-0.1.1.dist-info/LICENSE
cardboard_server-0.1.1.dist-info/METADATA
cardboard_server-0.1.1.dist-info/WHEEL
cardboard_server-0.1.1.dist-info/top_level.txt
cardboard_server-0.1.1.dist-info/RECORD
