Metadata-Version: 2.1
Name: cardboard-server
Version: 0.1.1
Summary: A Flask server for React data dashboards
Home-page: https://github.com/jasnkwan/cardboard
Author: Jason Kwan
Author-email: Jason Kwan <jasnkwan@gmail.com>
Project-URL: Homepage, https://github.com/jasnkwan/cardboard
Project-URL: Repository, https://github.com/jasnkwan/cardboard.git
Classifier: Programming Language :: Python :: 3
Classifier: Framework :: Flask
Classifier: License :: OSI Approved :: MIT License
Classifier: Operating System :: OS Independent
Requires-Python: >=3.7
License-File: LICENSE
Requires-Dist: asgiref==3.8.1
Requires-Dist: bidict==0.23.1
Requires-Dist: blinker==1.8.2
Requires-Dist: build==1.2.2.post1
Requires-Dist: certifi==2024.8.30
Requires-Dist: charset-normalizer==3.3.2
Requires-Dist: click==8.1.7
Requires-Dist: docutils==0.21.2
Requires-Dist: Flask==3.0.3
Requires-Dist: Flask-Cors==5.0.0
Requires-Dist: Flask-SocketIO==5.3.7
Requires-Dist: gunicorn==23.0.0
Requires-Dist: h11==0.14.0
Requires-Dist: idna==3.10
Requires-Dist: importlib-metadata==8.5.0
Requires-Dist: itsdangerous==2.2.0
Requires-Dist: jaraco.classes==3.4.0
Requires-Dist: jaraco.context==6.0.1
Requires-Dist: jaraco.functools==4.1.0
Requires-Dist: Jinja2==3.1.4
Requires-Dist: keyring==25.4.1
Requires-Dist: markdown-it-py==3.0.0
Requires-Dist: MarkupSafe==2.1.5
Requires-Dist: mdurl==0.1.2
Requires-Dist: more-itertools==10.5.0
Requires-Dist: nh3==0.2.18
Requires-Dist: packaging==24.1
Requires-Dist: pkginfo==1.10.0
Requires-Dist: Pygments==2.18.0
Requires-Dist: pyproject-hooks==1.2.0
Requires-Dist: python-engineio==4.9.1
Requires-Dist: python-socketio==5.11.4
Requires-Dist: readme-renderer==44.0
Requires-Dist: requests==2.32.3
Requires-Dist: requests-toolbelt==1.0.0
Requires-Dist: rfc3986==2.0.0
Requires-Dist: rich==13.8.1
Requires-Dist: setuptools==75.1.0
Requires-Dist: simple-websocket==1.0.0
Requires-Dist: toml==0.10.2
Requires-Dist: twine==5.1.1
Requires-Dist: urllib3==2.2.3
Requires-Dist: watchdog==5.0.3
Requires-Dist: websockets==13.1
Requires-Dist: Werkzeug==3.0.4
Requires-Dist: wheel==0.44.0
Requires-Dist: wsproto==1.2.0
Requires-Dist: zipp==3.20.2
